eurlparser/__init__.py
eurlparser/eurlparser.py
eurlparser-0.0.2.dist-info/LICENSE
eurlparser-0.0.2.dist-info/METADATA
eurlparser-0.0.2.dist-info/WHEEL
eurlparser-0.0.2.dist-info/top_level.txt
eurlparser-0.0.2.dist-info/RECORD
