Metadata-Version: 2.1
Name: eurlparser
Version: 0.0.2
Summary: A powerful URL parser with detailed analysis.
Home-page: https://github.com/keklick1337/eurlparser
Author: Vladislav Tislenko
Author-email: Vladislav Tislenko <keklick1337@gmail.com>
License: MIT
Project-URL: Homepage, https://github.com/keklick1337/eurlparser
Project-URL: Bug Tracker, https://github.com/keklick1337/eurlparser/issues
Keywords: url,parser,url-parser,enhanced-url-parser
Classifier: Development Status :: 4 - Beta
Classifier: Intended Audience :: Developers
Classifier: License :: OSI Approved :: MIT License
Classifier: Programming Language :: Python :: 3
Classifier: Programming Language :: Python :: 3.6
Classifier: Programming Language :: Python :: 3.7
Classifier: Programming Language :: Python :: 3.8
Classifier: Programming Language :: Python :: 3.9
Classifier: Programming Language :: Python :: 3.10
Classifier: Programming Language :: Python :: 3.11
Classifier: Programming Language :: Python :: 3.12
Requires-Python: >=3.6
License-File: LICENSE
Provides-Extra: dev
Requires-Dist: check-manifest ; extra == 'dev'
